[
    {
        "id": "1",
        "estado": "FREE",
        "posicion": [
            0,
            0
        ]
    },
    {
        "id": "2",
        "estado": "FREE",
        "posicion": [
            0,
            0
        ]
    },
    {
        "id": "3",
        "estado": "FREE",
        "posicion": [
            0,
            0
        ]
    },
    {
        "id": "4",
        "estado": "FREE",
        "posicion": [
            0,
            0
        ]
    },
    {
        "id": "5",
        "estado": "FREE",
        "posicion": [
            0,
            0
        ]
    },
    {
        "id": "6",
        "estado": "FREE",
        "posicion": [
            0,
            0
        ]
    },
    {
        "id": "7",
        "estado": "FREE",
        "posicion": [
            0,
            0
        ]
    },
    {
        "id": "8",
        "estado": "FREE",
        "posicion": [
            0,
            0
        ]
    },
    {
        "id": "9",
        "estado": "FREE",
        "posicion": [
            0,
            0
        ]
    }
]